aliyunsdkalinlp/__init__.py
aliyunsdkalinlp/endpoint.py
aliyunsdkalinlp/request/__init__.py
aliyunsdkalinlp/request/v20200629/ADClockRequest.py
aliyunsdkalinlp/request/v20200629/ADMMURequest.py
aliyunsdkalinlp/request/v20200629/ADMiniCogRequest.py
aliyunsdkalinlp/request/v20200629/ADMiniCogResultRequest.py
aliyunsdkalinlp/request/v20200629/DeleteServiceDataByConditionsRequest.py
aliyunsdkalinlp/request/v20200629/DeleteServiceDataByIdsRequest.py
aliyunsdkalinlp/request/v20200629/GetBrandChEcomRequest.py
aliyunsdkalinlp/request/v20200629/GetCateChEcomRequest.py
aliyunsdkalinlp/request/v20200629/GetCheckDuplicationChMedicalRequest.py
aliyunsdkalinlp/request/v20200629/GetDiagnosisChMedicalRequest.py
aliyunsdkalinlp/request/v20200629/GetDpChEcomRequest.py
aliyunsdkalinlp/request/v20200629/GetDpChGeneralCTBRequest.py
aliyunsdkalinlp/request/v20200629/GetDpChGeneralStanfordRequest.py
aliyunsdkalinlp/request/v20200629/GetEcChGeneralRequest.py
aliyunsdkalinlp/request/v20200629/GetEcEnGeneralRequest.py
aliyunsdkalinlp/request/v20200629/GetEmbeddingRequest.py
aliyunsdkalinlp/request/v20200629/GetItemPubChEcomRequest.py
aliyunsdkalinlp/request/v20200629/GetKeywordChEcomRequest.py
aliyunsdkalinlp/request/v20200629/GetKeywordEnEcomRequest.py
aliyunsdkalinlp/request/v20200629/GetMedicineChMedicalRequest.py
aliyunsdkalinlp/request/v20200629/GetNerChEcomRequest.py
aliyunsdkalinlp/request/v20200629/GetNerChMedicalRequest.py
aliyunsdkalinlp/request/v20200629/GetNerCustomizedChEcomRequest.py
aliyunsdkalinlp/request/v20200629/GetNerCustomizedSeaEcomRequest.py
aliyunsdkalinlp/request/v20200629/GetOpenNLUHighRecallRequest.py
aliyunsdkalinlp/request/v20200629/GetOpenNLURequest.py
aliyunsdkalinlp/request/v20200629/GetOperationChMedicalRequest.py
aliyunsdkalinlp/request/v20200629/GetPosChEcomRequest.py
aliyunsdkalinlp/request/v20200629/GetPosChGeneralRequest.py
aliyunsdkalinlp/request/v20200629/GetPriceChEcomRequest.py
aliyunsdkalinlp/request/v20200629/GetSSETestRequest.py
aliyun_python_sdk_alinlp-1.0.24.dist-info/LICENSE
aliyun_python_sdk_alinlp-1.0.24.dist-info/METADATA
aliyun_python_sdk_alinlp-1.0.24.dist-info/WHEEL
aliyun_python_sdk_alinlp-1.0.24.dist-info/top_level.txt
aliyun_python_sdk_alinlp-1.0.24.dist-info/RECORD
